mni/__init__.py
mni/numero.py
mni/soap/__init__.py
mni/soap/details.py
mni/soap/generic.py
mni-0.2.9.dist-info/METADATA
mni-0.2.9.dist-info/WHEEL
mni-0.2.9.dist-info/licenses/LICENSE
mni-0.2.9.dist-info/RECORD
