Metadata-Version: 2.4
Name: MNI
Version: 0.2.9
Summary: Modelo Nacional de Interoperabilidade
License-Expression: GPL-3.0
License-File: LICENSE
Keywords: cnj,mni,tjsp,mpsp
Author: Michel Metran
Author-email: michelmetran@gmail.com
Requires-Python: >=3.10
Classifier: Programming Language :: Python :: 3
Classifier: Operating System :: OS Independent
Classifier: License :: OSI Approved :: GNU General Public License v3 (GPLv3)
Classifier: Natural Language :: Portuguese (Brazilian)
Classifier: Intended Audience :: Developers
Requires-Dist: case-converter (>=1.1.0,<2.0.0)
Requires-Dist: notebook (>=7.3.3,<8.0.0)
Requires-Dist: pandas (>=2.2.2,<3.0.0)
Requires-Dist: python-dotenv (>=1.0.1,<2.0.0)
Requires-Dist: zeep (>=4.3.1,<5.0.0)
Project-URL: Documentation, https://pyMNI.readthedocs.io
Project-URL: Homepage, https://github.com/michelmetran/pyMNI
Project-URL: Issues, https://github.com/michelmetran/pyMNI/issues
Project-URL: Repository, https://github.com/michelmetran/pyMNI.git
